MANIFEST.in
setup.cfg
setup.py
tayra/__init__.py
tayra/ast.py
tayra/codegen.py
tayra/compiler.py
tayra/h.py
tayra/interfaces.py
tayra/lexer.py
tayra/parser.py
tayra/runtime.py
tayra/script.py
tayra/utils.py
tayra.egg-info/PKG-INFO
tayra.egg-info/SOURCES.txt
tayra.egg-info/dependency_links.txt
tayra.egg-info/entry_points.txt
tayra.egg-info/namespace_packages.txt
tayra.egg-info/not-zip-safe
tayra.egg-info/requires.txt
tayra.egg-info/top_level.txt
tayra/decorators/__init__.py
tayra/decorators/useragent.py
tayra/expr/__init__.py
tayra/expr/defaultpy.py
tayra/expr/evalpy.py
tayra/ext/__init__.py
tayra/ext/ttlpygment.py
tayra/ext/vim/.Attic/ftplugin/ttl.vim
tayra/ext/vim/ftdetect/tss.vim
tayra/ext/vim/ftdetect/ttl.vim
tayra/ext/vim/syntax/ttl.vim
tayra/filterblocks/__init__.py
tayra/filterblocks/pycode.py
tayra/tags/__init__.py
tayra/tags/forms.py
tayra/tags/html.py
tayra/test/__init__.py
tayra/test/teststd.py
tayra/test/bench/tayra/bigtable.ttl
tayra/test/bench/tayra/footer.ttl
tayra/test/bench/tayra/header.ttl
tayra/test/bench/tayra/template.ttl
tayra/test/stdttl/attributes.ttl
tayra/test/stdttl/base.ttl
tayra/test/stdttl/basic.ttl
tayra/test/stdttl/body.ttl
tayra/test/stdttl/comments.ttl
tayra/test/stdttl/context.ttl
tayra/test/stdttl/doctype.ttl
tayra/test/stdttl/element.ttl
tayra/test/stdttl/empty.ttl
tayra/test/stdttl/escapes.ttl
tayra/test/stdttl/escfilters.ttl
tayra/test/stdttl/example1.ttl
tayra/test/stdttl/exprs.ttl
tayra/test/stdttl/exprs1.ttl
tayra/test/stdttl/fb_pycode.ttl
tayra/test/stdttl/forblock.ttl
tayra/test/stdttl/func_decorator.ttl
tayra/test/stdttl/funcblock.ttl
tayra/test/stdttl/html5.ttl
tayra/test/stdttl/ifblock.ttl
tayra/test/stdttl/implementer.ttl
tayra/test/stdttl/import.ttl
tayra/test/stdttl/inherit.ttl
tayra/test/stdttl/inlinetag.ttl
tayra/test/stdttl/latin1.ttl
tayra/test/stdttl/loopcontrol.ttl
tayra/test/stdttl/nestedtags.ttl
tayra/test/stdttl/obfus1.ttl
tayra/test/stdttl/stripsyntax.ttl
tayra/test/stdttl/style.ttl
tayra/test/stdttl/tag.ttl
tayra/test/stdttl/tagcont.ttl
tayra/test/stdttl/templaterule.ttl
tayra/test/stdttl/useinterface.ttl
tayra/test/stdttl/utf8.ttl
tayra/test/stdttl/whileblock.ttl
tayra/test/stdttl/ref/attributes.html
tayra/test/stdttl/ref/attributes.ttl.py
