Metadata-Version: 1.1
Name: tayra
Version: 0.44dev
Summary: An integrated web templating environment
Home-page: http://pythonhosted.org/tayra/
Author: prataprc
Author-email: prataprc@gmail.com
License: General Public License
Keywords: template, web, html, css, pluggdapps
Platform: 
Classifier: Development Status :: 4 - Beta
Classifier: Environment :: Web Environment
Classifier: Intended Audience :: Developers
Classifier: Programming Language :: Python :: 3.2
Classifier: Topic :: Internet :: WWW/HTTP :: Dynamic Content
Provides: tayra
